prime/__init__.py
prime/config.py
prime/exceptions.py
prime/prime.py
prime/types.py
prime/adapters/__init__.py
prime/adapters/langchain.py
prime/adapters/llamaindex.py
prime/api/__init__.py
prime/api/app.py
prime/api/dependencies.py
prime/api/models.py
prime/api/middleware/__init__.py
prime/api/middleware/auth.py
prime/api/middleware/logging.py
prime/api/middleware/rate_limit.py
prime/api/routes/__init__.py
prime/api/routes/clusters.py
prime/api/routes/config.py
prime/api/routes/diagnostics.py
prime/api/routes/memory.py
prime/api/routes/process.py
prime/client/__init__.py
prime/client/client.py
prime/encoder/__init__.py
prime/encoder/config.py
prime/encoder/exceptions.py
prime/encoder/pooling.py
prime/encoder/protocols.py
prime/encoder/y_encoder.py
prime/evaluation/__init__.py
prime/evaluation/ragas.py
prime/evaluation/types.py
prime/mcs/__init__.py
prime/mcs/cluster.py
prime/mcs/exceptions.py
prime/mcs/index.py
prime/mcs/mcs.py
prime/mcs/mcs_config.py
prime/mcs/memory_index.py
prime/mcs/qdrant_index.py
prime/mcs/sparse.py
prime/mcs/types.py
prime/predictor/__init__.py
prime/predictor/config.py
prime/predictor/exceptions.py
prime/predictor/optimized.py
prime/predictor/predictor.py
prime/predictor/types.py
prime/ssm/__init__.py
prime/ssm/exceptions.py
prime/ssm/ssm.py
prime/ssm/ssm_config.py
prime/ssm/ssm_types.py
prime/training/__init__.py
prime/training/losses.py
prime/training/trainer.py
prime_rag-0.1.0.dist-info/METADATA
prime_rag-0.1.0.dist-info/WHEEL
prime_rag-0.1.0.dist-info/licenses/LICENSE
prime_rag-0.1.0.dist-info/RECORD
