Metadata-Version: 2.4
Name: prime-rag
Version: 0.1.0
Summary: Predictive Retrieval with Intelligent Memory Embeddings
Project-URL: Homepage, https://github.com/Mathews-Tom/PRIME
Project-URL: Documentation, https://github.com/Mathews-Tom/PRIME#readme
Project-URL: Repository, https://github.com/Mathews-Tom/PRIME.git
Project-URL: Issues, https://github.com/Mathews-Tom/PRIME/issues
Author: AetherForge
License: MIT
License-File: LICENSE
Keywords: embeddings,jepa,llm,memory,predictive,rag,retrieval
Classifier: Development Status :: 3 - Alpha
Classifier: Intended Audience :: Developers
Classifier: License :: OSI Approved :: MIT License
Classifier: Programming Language :: Python :: 3
Classifier: Programming Language :: Python :: 3.12
Classifier: Programming Language :: Python :: 3.13
Classifier: Topic :: Scientific/Engineering :: Artificial Intelligence
Requires-Python: >=3.12
Requires-Dist: fastapi>=0.128.0
Requires-Dist: llama-index-core>=0.14.12
Requires-Dist: numpy>=1.26.0
Requires-Dist: onnxscript>=0.5.7
Requires-Dist: pydantic>=2.0.0
Requires-Dist: qdrant-client>=1.16.2
Requires-Dist: ragas>=0.4.2
Requires-Dist: structlog>=25.5.0
Requires-Dist: torch>=2.0.0
Requires-Dist: transformers>=4.40.0
Requires-Dist: uvicorn>=0.40.0
Provides-Extra: all
Requires-Dist: faiss-cpu>=1.8.0; extra == 'all'
Requires-Dist: sentence-transformers>=2.7.0; extra == 'all'
Provides-Extra: dev
Requires-Dist: mypy>=1.10.0; extra == 'dev'
Requires-Dist: pytest-asyncio>=0.23.0; extra == 'dev'
Requires-Dist: pytest-cov>=4.1.0; extra == 'dev'
Requires-Dist: pytest>=8.0.0; extra == 'dev'
Requires-Dist: ruff>=0.4.0; extra == 'dev'
